setup.py
odoo/addons/oficinavirtual_somconnexio/CHANGELOG.md
odoo/addons/oficinavirtual_somconnexio/README.rst
odoo/addons/oficinavirtual_somconnexio/__init__.py
odoo/addons/oficinavirtual_somconnexio/__manifest__.py
odoo/addons/oficinavirtual_somconnexio/data/ir_config_pararameter.xml
odoo/addons/oficinavirtual_somconnexio/i18n/ca_ES.po
odoo/addons/oficinavirtual_somconnexio/i18n/es.po
odoo/addons/oficinavirtual_somconnexio/listeners/__init__.py
odoo/addons/oficinavirtual_somconnexio/listeners/res_partner_listener.py
odoo/addons/oficinavirtual_somconnexio/models/__init__.py
odoo/addons/oficinavirtual_somconnexio/models/res_partner.py
odoo/addons/oficinavirtual_somconnexio/services/__init__.py
odoo/addons/oficinavirtual_somconnexio/services/change_partner_emails.py
odoo/addons/oficinavirtual_somconnexio/somoffice/__init__.py
odoo/addons/oficinavirtual_somconnexio/somoffice/errors.py
odoo/addons/oficinavirtual_somconnexio/somoffice/user.py
odoo/addons/oficinavirtual_somconnexio/tests/__init__.py
odoo/addons/oficinavirtual_somconnexio/tests/listeners/__init__.py
odoo/addons/oficinavirtual_somconnexio/tests/listeners/test_res_partner_listener.py
odoo/addons/oficinavirtual_somconnexio/tests/models/__init__.py
odoo/addons/oficinavirtual_somconnexio/tests/models/test_res_partner.py
odoo/addons/oficinavirtual_somconnexio/tests/services/__init__.py
odoo/addons/oficinavirtual_somconnexio/tests/services/test_change_partner_emails.py
odoo/addons/oficinavirtual_somconnexio/tests/somoffice/__init__.py
odoo/addons/oficinavirtual_somconnexio/tests/somoffice/test_user.py
odoo/addons/oficinavirtual_somconnexio/tests/wizards/__init__.py
odoo/addons/oficinavirtual_somconnexio/tests/wizards/test_partner_check_somoffice_email.py
odoo/addons/oficinavirtual_somconnexio/tests/wizards/test_partner_email_change.py
odoo/addons/oficinavirtual_somconnexio/wizards/__init__.py
odoo/addons/oficinavirtual_somconnexio/wizards/partner_check_somoffice_email/__init__.py
odoo_addon_oficinavirtual_somconnexio.egg-info/PKG-INFO
odoo_addon_oficinavirtual_somconnexio.egg-info/SOURCES.txt
odoo_addon_oficinavirtual_somconnexio.egg-info/dependency_links.txt
odoo_addon_oficinavirtual_somconnexio.egg-info/not-zip-safe
odoo_addon_oficinavirtual_somconnexio.egg-info/requires.txt
odoo_addon_oficinavirtual_somconnexio.egg-info/top_level.txt