Metadata-Version: 2.4
Name: odoo-addon-oficinavirtual_somconnexio
Version: 16.0.1.0.3
Summary: Integrates office virtual functionalities specific to Som Connexió.
Home-page: https://git.coopdevs.org/coopdevs/som-connexio/odoo/odoo-somconnexio
Author: Som Connexió SCCL, Coopdevs Treball SCCL
License: AGPL-3
Classifier: Programming Language :: Python
Classifier: Framework :: Odoo
Classifier: Framework :: Odoo :: 16.0
Classifier: License :: OSI Approved :: GNU Affero General Public License v3
Requires-Python: >=3.10
Requires-Dist: odoo-addon-res_partner_api_somconnexio<16.1dev,>=16.0dev
Requires-Dist: odoo<16.1dev,>=16.0a
Dynamic: author
Dynamic: classifier
Dynamic: description
Dynamic: home-page
Dynamic: license
Dynamic: requires-dist
Dynamic: requires-python
Dynamic: summary
